libvinput.cp39-win_amd64.pyd
libvinput-1.4.dist-info/LICENSE
libvinput-1.4.dist-info/METADATA
libvinput-1.4.dist-info/WHEEL
libvinput-1.4.dist-info/top_level.txt
libvinput-1.4.dist-info/RECORD
