Metadata-Version: 2.1
Name: libvinput
Version: 1.4
Summary: Python interface for libvinput
Author: Slendi
License-File: LICENSE
